[{"age":"<1","total":{"people":"135430","percentOfTotal":2.0554951826465997},"male":{"people":"69410","percentOfTotal":1.0534735333936387},"female":{"people":"66020","percentOfTotal":1.002021649252961}},{"age":"1","total":{"people":"139440","percentOfTotal":2.116357145892652},"male":{"people":"71205","percentOfTotal":1.0807172301583927},"female":{"people":"68235","percentOfTotal":1.0356399157342595}},{"age":"2","total":{"people":"141430","percentOfTotal":2.146560464311516},"male":{"people":"72610","percentOfTotal":1.1020416836149274},"female":{"people":"68820","percentOfTotal":1.0445187806965885}},{"age":"3","total":{"people":"144535","percentOfTotal":2.19368674757311},"male":{"people":"74005","percentOfTotal":1.1232143616020203},"female":{"people":"70530","percentOfTotal":1.0704723859710896}},{"age":"4","total":{"people":"143425","percentOfTotal":2.1768396704651005},"male":{"people":"73365","percentOfTotal":1.1135007315577627},"female":{"people":"70065","percentOfTotal":1.0634148266420589}},{"age":"5","total":{"people":"141800","percentOfTotal":2.1521761566808526},"male":{"people":"72690","percentOfTotal":1.1032558873704597},"female":{"people":"69115","percentOfTotal":1.0489961570451136}},{"age":"6","total":{"people":"142165","percentOfTotal":2.157715961315468},"male":{"people":"72990","percentOfTotal":1.1078091514537056},"female":{"people":"69175","percentOfTotal":1.0499068098617628}},{"age":"7","total":{"people":"143950","percentOfTotal":2.184807882610781},"male":{"people":"73940","percentOfTotal":1.1222278210506504},"female":{"people":"70015","percentOfTotal":1.062655949294851}},{"age":"8","total":{"people":"141355","percentOfTotal":2.1454221482907045},"male":{"people":"72295","percentOfTotal":1.0972607563275192},"female":{"people":"69065","percentOfTotal":1.048237279697906}},{"age":"9","total":{"people":"143480","percentOfTotal":2.177674435547029},"male":{"people":"73370","percentOfTotal":1.1135766192924834},"female":{"people":"70105","percentOfTotal":1.064021928519825}},{"age":"10","total":{"people":"145195","percentOfTotal":2.203703928556251},"male":{"people":"74455","percentOfTotal":1.1300442577268892},"female":{"people":"70740","percentOfTotal":1.073659670829362}},{"age":"11","total":{"people":"150865","percentOfTotal":2.2897606197295968},"male":{"people":"77555","percentOfTotal":1.1770946532537625},"female":{"people":"73305","percentOfTotal":1.1125900787411136}},{"age":"12","total":{"people":"151080","percentOfTotal":2.2930237923225896},"male":{"people":"77210","percentOfTotal":1.1718583995580298},"female":{"people":"73870","percentOfTotal":1.1211653927645597}},{"age":"13","total":{"people":"156375","percentOfTotal":2.373388903391878},"male":{"people":"80160","percentOfTotal":1.2166321630432801},"female":{"people":"76220","percentOfTotal":1.1568326280833188}},{"age":"14","total":{"people":"160235","percentOfTotal":2.4319742345963076},"male":{"people":"82250","percentOfTotal":1.2483532361565595},"female":{"people":"77990","percentOfTotal":1.183696886174469}},{"age":"15","total":{"people":"168840","percentOfTotal":2.5625770260507417},"male":{"people":"86700","percentOfTotal":1.315893320058039},"female":{"people":"82140","percentOfTotal":1.2466837059927027}},{"age":"16","total":{"people":"172840","percentOfTotal":2.6232872138273526},"male":{"people":"89195","percentOfTotal":1.3537612996836998},"female":{"people":"83645","percentOfTotal":1.2695259141436523}},{"age":"17","total":{"people":"171400","percentOfTotal":2.6014315462277726},"male":{"people":"88230","percentOfTotal":1.3391149668825926},"female":{"people":"83170","percentOfTotal":1.26231657934518}},{"age":"18","total":{"people":"173925","percentOfTotal":2.639754852261758},"male":{"people":"89220","percentOfTotal":1.3541407383573039},"female":{"people":"84705","percentOfTotal":1.2856141139044543}},{"age":"19","total":{"people":"176620","percentOfTotal":2.6806583412762497},"male":{"people":"90335","percentOfTotal":1.371063703200034},"female":{"people":"86290","percentOfTotal":1.3096705258109365}},{"age":"20","total":{"people":"177790","percentOfTotal":2.698416071200908},"male":{"people":"91045","percentOfTotal":1.3818397615303826},"female":{"people":"86745","percentOfTotal":1.3165763096705259}},{"age":"21","total":{"people":"177505","percentOfTotal":2.6940904703218247},"male":{"people":"90240","percentOfTotal":1.3696218362403396},"female":{"people":"87270","percentOfTotal":1.324544521816206}},{"age":"22","total":{"people":"169385","percentOfTotal":2.570848789135305},"male":{"people":"86090","percentOfTotal":1.3066350164221059},"female":{"people":"83290","percentOfTotal":1.2641378849784783}},{"age":"23","total":{"people":"163955","percentOfTotal":2.4884347092285557},"male":{"people":"82605","percentOfTotal":1.2537412653217335},"female":{"people":"81345","percentOfTotal":1.2346175561721013}},{"age":"24","total":{"people":"164275","percentOfTotal":2.4932915242506843},"male":{"people":"82510","percentOfTotal":1.2522993983620392},"female":{"people":"81765","percentOfTotal":1.2409921258886454}},{"age":"25","total":{"people":"165895","percentOfTotal":2.517879150300212},"male":{"people":"82640","percentOfTotal":1.254272479464779},"female":{"people":"83255","percentOfTotal":1.263606670835433}},{"age":"26","total":{"people":"164890","percentOfTotal":2.5026257156213387},"male":{"people":"81780","percentOfTotal":1.2412197890928076},"female":{"people":"83110","percentOfTotal":1.261405926528531}},{"age":"27","total":{"people":"162025","percentOfTotal":2.459142043626341},"male":{"people":"79450","percentOfTotal":1.205856104712932},"female":{"people":"82575","percentOfTotal":1.253285938913409}},{"age":"28","total":{"people":"162910","percentOfTotal":2.472574172671916},"male":{"people":"79505","percentOfTotal":1.2066908697948602},"female":{"people":"83400","percentOfTotal":1.2658074151423349}},{"age":"29","total":{"people":"159410","percentOfTotal":2.419452758367382},"male":{"people":"76670","percentOfTotal":1.1636625242081873},"female":{"people":"82735","percentOfTotal":1.2557143464244735}},{"age":"30","total":{"people":"162615","percentOfTotal":2.4680967963233913},"male":{"people":"78500","percentOfTotal":1.1914374351159869},"female":{"people":"84115","percentOfTotal":1.2766593612074042}},{"age":"31","total":{"people":"160050","percentOfTotal":2.4291663884116392},"male":{"people":"76925","percentOfTotal":1.1675327986789463},"female":{"people":"83130","percentOfTotal":1.2617094774674138}},{"age":"32","total":{"people":"158335","percentOfTotal":2.4031368954024175},"male":{"people":"75485","percentOfTotal":1.1456771310793665},"female":{"people":"82845","percentOfTotal":1.2573838765883303}},{"age":"33","total":{"people":"158145","percentOfTotal":2.4002531614830285},"male":{"people":"75525","percentOfTotal":1.1462842329571326},"female":{"people":"82620","percentOfTotal":1.253968928525896}},{"age":"34","total":{"people":"161220","percentOfTotal":2.446924118336298},"male":{"people":"76900","percentOfTotal":1.1671533600053425},"female":{"people":"84320","percentOfTotal":1.2797707583309554}},{"age":"35","total":{"people":"164795","percentOfTotal":2.501183848661644},"male":{"people":"78920","percentOfTotal":1.197812004832531},"female":{"people":"85880","percentOfTotal":1.3034477315638338}},{"age":"36","total":{"people":"168270","percentOfTotal":2.553925824292574},"male":{"people":"80495","percentOfTotal":1.2217166412695715},"female":{"people":"87775","percentOfTotal":1.3322091830230032}},{"age":"37","total":{"people":"166020","percentOfTotal":2.519776343668231},"male":{"people":"79610","percentOfTotal":1.2082845122239962},"female":{"people":"86410","percentOfTotal":1.3114918314442348}},{"age":"38","total":{"people":"170185","percentOfTotal":2.582990826690627},"male":{"people":"82285","percentOfTotal":1.2488844502996048},"female":{"people":"87900","percentOfTotal":1.3341063763910221}},{"age":"39","total":{"people":"175070","percentOfTotal":2.6571331435128127},"male":{"people":"84540","percentOfTotal":1.2831098186586691},"female":{"people":"90525","percentOfTotal":1.373947437119423}},{"age":"40","total":{"people":"186170","percentOfTotal":2.8256039145929077},"male":{"people":"90135","percentOfTotal":1.3680281938112036},"female":{"people":"96035","percentOfTotal":1.4575757207817044}},{"age":"41","total":{"people":"184045","percentOfTotal":2.793351627336583},"male":{"people":"89215","percentOfTotal":1.354064850622583},"female":{"people":"94825","percentOfTotal":1.4392108889792796}},{"age":"42","total":{"people":"184360","percentOfTotal":2.7981325546239915},"male":{"people":"89430","percentOfTotal":1.3573280232155758},"female":{"people":"94935","percentOfTotal":1.4408804191431364}},{"age":"43","total":{"people":"183260","percentOfTotal":2.781437252985423},"male":{"people":"88945","percentOfTotal":1.3499669129476617},"female":{"people":"94315","percentOfTotal":1.4314703400377617}},{"age":"44","total":{"people":"186245","percentOfTotal":2.826742230613719},"male":{"people":"90195","percentOfTotal":1.3689388466278527},"female":{"people":"96055","percentOfTotal":1.4578792717205875}},{"age":"45","total":{"people":"199320","percentOfTotal":3.025188656908516},"male":{"people":"97850","percentOfTotal":1.4851229684853415},"female":{"people":"101470","percentOfTotal":1.5400656884231745}},{"age":"46","total":{"people":"212510","percentOfTotal":3.2253805011018897},"male":{"people":"103510","percentOfTotal":1.571027884189246},"female":{"people":"109000","percentOfTotal":1.6543526169126441}},{"age":"47","total":{"people":"217040","percentOfTotal":3.294134788758902},"male":{"people":"106560","percentOfTotal":1.6173194023689115},"female":{"people":"110485","percentOfTotal":1.6768912741247108}},{"age":"48","total":{"people":"216790","percentOfTotal":3.2903404020228635},"male":{"people":"106590","percentOfTotal":1.6177747287772362},"female":{"people":"110200","percentOfTotal":1.6725656732456275}},{"age":"49","total":{"people":"210215","percentOfTotal":3.19054803086506},"male":{"people":"102995","percentOfTotal":1.5632114475130072},"female":{"people":"107215","percentOfTotal":1.6272606956173317}},{"age":"50","total":{"people":"213185","percentOfTotal":3.2356253452891925},"male":{"people":"104280","percentOfTotal":1.5827145953362436},"female":{"people":"108905","percentOfTotal":1.6529107499529496}},{"age":"51","total":{"people":"206420","percentOfTotal":3.1329492402119996},"male":{"people":"101145","percentOfTotal":1.5351329856663245},"female":{"people":"105275","percentOfTotal":1.5978162545456753}},{"age":"52","total":{"people":"199725","percentOfTotal":3.031335563420898},"male":{"people":"97910","percentOfTotal":1.4860336213019907},"female":{"people":"101820","percentOfTotal":1.5453778298536276}},{"age":"53","total":{"people":"195920","percentOfTotal":2.9735849972983965},"male":{"people":"96020","percentOfTotal":1.457348057577542},"female":{"people":"99905","percentOfTotal":1.5163128274555753}},{"age":"54","total":{"people":"190885","percentOfTotal":2.897166048434588},"male":{"people":"93215","percentOfTotal":1.4147750383991937},"female":{"people":"97670","percentOfTotal":1.4823910100353939}},{"age":"55","total":{"people":"184245","percentOfTotal":2.796387136725414},"male":{"people":"89595","percentOfTotal":1.359832318461361},"female":{"people":"94645","percentOfTotal":1.4364789305293322}},{"age":"56","total":{"people":"181930","percentOfTotal":2.7612511155497},"male":{"people":"88290","percentOfTotal":1.3400256196992417},"female":{"people":"93640","percentOfTotal":1.4212254958504587}},{"age":"57","total":{"people":"172965","percentOfTotal":2.625184407195371},"male":{"people":"83445","percentOfTotal":1.2664904047548218},"female":{"people":"89520","percentOfTotal":1.3586940024405496}},{"age":"58","total":{"people":"166205","percentOfTotal":2.5225841898528993},"male":{"people":"80370","percentOfTotal":1.2198194479015525},"female":{"people":"85830","percentOfTotal":1.302688854216626}},{"age":"59","total":{"people":"159285","percentOfTotal":2.4175555649993625},"male":{"people":"77055","percentOfTotal":1.1695058797816862},"female":{"people":"82225","percentOfTotal":1.2479737974829557}},{"age":"60","total":{"people":"156740","percentOfTotal":2.378928708026494},"male":{"people":"76175","percentOfTotal":1.1561496384708319},"female":{"people":"80560","percentOfTotal":1.2227031818209415}},{"age":"61","total":{"people":"152835","percentOfTotal":2.3196603872095776},"male":{"people":"73670","percentOfTotal":1.1181298833757294},"female":{"people":"79165","percentOfTotal":1.2015305038338484}},{"age":"62","total":{"people":"150600","percentOfTotal":2.2857385697893964},"male":{"people":"72730","percentOfTotal":1.1038629892482257},"female":{"people":"77865","percentOfTotal":1.18179969280645}},{"age":"63","total":{"people":"152400","percentOfTotal":2.313058154288871},"male":{"people":"73685","percentOfTotal":1.1183575465798916},"female":{"people":"78710","percentOfTotal":1.1946247199742588}},{"age":"64","total":{"people":"153085","percentOfTotal":2.323454773945616},"male":{"people":"74105","percentOfTotal":1.1247321162964357},"female":{"people":"78975","percentOfTotal":1.1986467699144594}},{"age":"65","total":{"people":"122835","percentOfTotal":1.8643339788849966},"male":{"people":"59280","percentOfTotal":0.8997249828493721},"female":{"people":"63555","percentOfTotal":0.9646089960356248}},{"age":"66","total":{"people":"115975","percentOfTotal":1.7602160068481092},"male":{"people":"55850","percentOfTotal":0.8476659968309282},"female":{"people":"60125","percentOfTotal":0.9125500100171811}},{"age":"67","total":{"people":"114095","percentOfTotal":1.731682218593102},"male":{"people":"54905","percentOfTotal":0.8333232149687039},"female":{"people":"59190","percentOfTotal":0.8983590036243981}},{"age":"68","total":{"people":"109425","percentOfTotal":1.660803074363909},"male":{"people":"52615","percentOfTotal":0.7985666324665942},"female":{"people":"56810","percentOfTotal":0.8622364418973149}},{"age":"69","total":{"people":"101155","percentOfTotal":1.5352847611357663},"male":{"people":"48225","percentOfTotal":0.7319372013817639},"female":{"people":"52935","percentOfTotal":0.8034234474887232}},{"age":"70","total":{"people":"96250","percentOfTotal":1.4608388933746972},"male":{"people":"45440","percentOfTotal":0.6896677331422986},"female":{"people":"50810","percentOfTotal":0.7711711602323986}},{"age":"71","total":{"people":"91390","percentOfTotal":1.387076015226115},"male":{"people":"42765","percentOfTotal":0.6490677950666901},"female":{"people":"48630","percentOfTotal":0.7380841078941458}},{"age":"72","total":{"people":"88850","percentOfTotal":1.3485250459879674},"male":{"people":"41420","percentOfTotal":0.6286539944268047},"female":{"people":"47430","percentOfTotal":0.7198710515611625}},{"age":"73","total":{"people":"84370","percentOfTotal":1.280529635678163},"male":{"people":"39560","percentOfTotal":0.6004237571106807},"female":{"people":"44810","percentOfTotal":0.6801058785674824}},{"age":"74","total":{"people":"79915","percentOfTotal":1.2129136640419629},"male":{"people":"37165","percentOfTotal":0.5640735321794351},"female":{"people":"42755","percentOfTotal":0.6489160195972487}},{"age":"75","total":{"people":"78220","percentOfTotal":1.187187721971624},"male":{"people":"35985","percentOfTotal":0.5461640267853348},"female":{"people":"42235","percentOfTotal":0.6410236951862892}},{"age":"76","total":{"people":"74040","percentOfTotal":1.1237455757450658},"male":{"people":"33955","percentOfTotal":0.5153536064887049},"female":{"people":"40090","percentOfTotal":0.6084678569910817}},{"age":"77","total":{"people":"69840","percentOfTotal":1.0599998785796245},"male":{"people":"31730","percentOfTotal":0.4815835645379651},"female":{"people":"38110","percentOfTotal":0.5784163140416594}},{"age":"78","total":{"people":"68495","percentOfTotal":1.039586077939739},"male":{"people":"30705","percentOfTotal":0.4660265789202086},"female":{"people":"37785","percentOfTotal":0.5734836112848097}},{"age":"79","total":{"people":"65555","percentOfTotal":0.9949640899239302},"male":{"people":"28970","percentOfTotal":0.43969353497210373},"female":{"people":"36585","percentOfTotal":0.5552705549518265}},{"age":"80","total":{"people":"63995","percentOfTotal":0.9712871166910519},"male":{"people":"27970","percentOfTotal":0.424515988027951},"female":{"people":"36025","percentOfTotal":0.546771128663101}},{"age":"81","total":{"people":"58655","percentOfTotal":0.8902390160092765},"male":{"people":"25115","percentOfTotal":0.381184091502395},"female":{"people":"33540","percentOfTotal":0.5090549245068815}},{"age":"82","total":{"people":"53335","percentOfTotal":0.8094944662663842},"male":{"people":"22205","percentOfTotal":0.3370174298949106},"female":{"people":"31125","percentOfTotal":0.4724011486367527}},{"age":"83","total":{"people":"50175","percentOfTotal":0.7615334179228616},"male":{"people":"20375","percentOfTotal":0.3092425189871112},"female":{"people":"29805","percentOfTotal":0.4523667866704712}},{"age":"84","total":{"people":"45355","percentOfTotal":0.6883776416520456},"male":{"people":"17955","percentOfTotal":0.2725128553822617},"female":{"people":"27405","percentOfTotal":0.4159406740045047}},{"age":"85","total":{"people":"42000","percentOfTotal":0.6374569716544133},"male":{"people":"15800","percentOfTotal":0.23980524171761264},"female":{"people":"26200","percentOfTotal":0.39765172993680065}},{"age":"86","total":{"people":"37400","percentOfTotal":0.5676402557113108},"male":{"people":"13520","percentOfTotal":0.20520043468494448},"female":{"people":"23880","percentOfTotal":0.3624398210263664}},{"age":"87","total":{"people":"33335","percentOfTotal":0.5059435273833301},"male":{"people":"11640","percentOfTotal":0.1766666464299374},"female":{"people":"21695","percentOfTotal":0.3292768809533928}},{"age":"88","total":{"people":"28470","percentOfTotal":0.43210476150002736},"male":{"people":"9475","percentOfTotal":0.1438072572958468},"female":{"people":"18990","percentOfTotal":0.2882216164694597}},{"age":"89","total":{"people":"24575","percentOfTotal":0.37298821615255257},"male":{"people":"7980","percentOfTotal":0.12111682461433852},"female":{"people":"16600","percentOfTotal":0.2519472792729348}},{"age":"90","total":{"people":"20695","percentOfTotal":0.31409933400924006},"male":{"people":"6650","percentOfTotal":0.10093068717861545},"female":{"people":"14040","percentOfTotal":0.2130927590959039}},{"age":"91","total":{"people":"16095","percentOfTotal":0.24428261806613769},"male":{"people":"4825","percentOfTotal":0.07323166400553677},"female":{"people":"11275","percentOfTotal":0.17112684179532167}},{"age":"92","total":{"people":"10995","percentOfTotal":0.1668771286509589},"male":{"people":"3015","percentOfTotal":0.04576030403662039},"female":{"people":"7980","percentOfTotal":0.12111682461433852}},{"age":"93","total":{"people":"8605","percentOfTotal":0.130602791454434},"male":{"people":"2375","percentOfTotal":0.03604667399236266},"female":{"people":"6235","percentOfTotal":0.09463200519679207}},{"age":"94","total":{"people":"6865","percentOfTotal":0.10419385977160826},"male":{"people":"1795","percentOfTotal":0.027243696764754095},"female":{"people":"5070","percentOfTotal":0.07695016300685419}},{"age":"95","total":{"people":"5300","percentOfTotal":0.08044099880400929},"male":{"people":"1290","percentOfTotal":0.01957903555795698},"female":{"people":"4010","percentOfTotal":0.06086196324605232}},{"age":"96","total":{"people":"4015","percentOfTotal":0.06093785098077308},"male":{"people":"970","percentOfTotal":0.014722220535828119},"female":{"people":"3050","percentOfTotal":0.04629151817966573}},{"age":"97","total":{"people":"2805","percentOfTotal":0.04257301917834832},"male":{"people":"610","percentOfTotal":0.009258303635933145},"female":{"people":"2195","percentOfTotal":0.03331471554241518}},{"age":"98","total":{"people":"1945","percentOfTotal":0.029520328806377002},"male":{"people":"445","percentOfTotal":0.006754008390147951},"female":{"people":"1500","percentOfTotal":0.022766320416229047}},{"age":"99","total":{"people":"1265","percentOfTotal":0.019199596884353163},"male":{"people":"225","percentOfTotal":0.003414948062434357},"female":{"people":"1040","percentOfTotal":0.015784648821918806}},{"age":"100+","total":{"people":"2025","percentOfTotal":0.030734532561909212},"male":{"people":"320","percentOfTotal":0.004856815022128863},"female":{"people":"1710","percentOfTotal":0.025953605274501114}}]