[{"age":"<1","total":{"people":"1090","percentOfTotal":3.3486943164362524},"male":{"people":"560","percentOfTotal":1.7204301075268817},"female":{"people":"530","percentOfTotal":1.6282642089093702}},{"age":"1","total":{"people":"1095","percentOfTotal":3.3640552995391704},"male":{"people":"555","percentOfTotal":1.705069124423963},"female":{"people":"540","percentOfTotal":1.6589861751152075}},{"age":"2","total":{"people":"1105","percentOfTotal":3.3947772657450073},"male":{"people":"550","percentOfTotal":1.6897081413210446},"female":{"people":"560","percentOfTotal":1.7204301075268817}},{"age":"3","total":{"people":"1190","percentOfTotal":3.655913978494624},"male":{"people":"615","percentOfTotal":1.889400921658986},"female":{"people":"575","percentOfTotal":1.7665130568356373}},{"age":"4","total":{"people":"1080","percentOfTotal":3.317972350230415},"male":{"people":"545","percentOfTotal":1.6743471582181262},"female":{"people":"535","percentOfTotal":1.6436251920122886}},{"age":"5","total":{"people":"1085","percentOfTotal":3.3333333333333335},"male":{"people":"555","percentOfTotal":1.705069124423963},"female":{"people":"530","percentOfTotal":1.6282642089093702}},{"age":"6","total":{"people":"1065","percentOfTotal":3.2718894009216593},"male":{"people":"545","percentOfTotal":1.6743471582181262},"female":{"people":"525","percentOfTotal":1.6129032258064515}},{"age":"7","total":{"people":"1080","percentOfTotal":3.317972350230415},"male":{"people":"565","percentOfTotal":1.7357910906298002},"female":{"people":"515","percentOfTotal":1.5821812596006144}},{"age":"8","total":{"people":"1060","percentOfTotal":3.2565284178187404},"male":{"people":"545","percentOfTotal":1.6743471582181262},"female":{"people":"520","percentOfTotal":1.597542242703533}},{"age":"9","total":{"people":"1120","percentOfTotal":3.4408602150537635},"male":{"people":"585","percentOfTotal":1.7972350230414749},"female":{"people":"540","percentOfTotal":1.6589861751152075}},{"age":"10","total":{"people":"1120","percentOfTotal":3.4408602150537635},"male":{"people":"560","percentOfTotal":1.7204301075268817},"female":{"people":"565","percentOfTotal":1.7357910906298002}},{"age":"11","total":{"people":"1080","percentOfTotal":3.317972350230415},"male":{"people":"555","percentOfTotal":1.705069124423963},"female":{"people":"525","percentOfTotal":1.6129032258064515}},{"age":"12","total":{"people":"1115","percentOfTotal":3.4254992319508446},"male":{"people":"540","percentOfTotal":1.6589861751152075},"female":{"people":"575","percentOfTotal":1.7665130568356373}},{"age":"13","total":{"people":"1105","percentOfTotal":3.3947772657450073},"male":{"people":"535","percentOfTotal":1.6436251920122886},"female":{"people":"570","percentOfTotal":1.7511520737327189}},{"age":"14","total":{"people":"1105","percentOfTotal":3.3947772657450073},"male":{"people":"600","percentOfTotal":1.8433179723502304},"female":{"people":"505","percentOfTotal":1.5514592933947773}},{"age":"15","total":{"people":"1135","percentOfTotal":3.4869431643625193},"male":{"people":"605","percentOfTotal":1.8586789554531489},"female":{"people":"530","percentOfTotal":1.6282642089093702}},{"age":"16","total":{"people":"1120","percentOfTotal":3.4408602150537635},"male":{"people":"560","percentOfTotal":1.7204301075268817},"female":{"people":"565","percentOfTotal":1.7357910906298002}},{"age":"17","total":{"people":"1160","percentOfTotal":3.5637480798771124},"male":{"people":"590","percentOfTotal":1.8125960061443933},"female":{"people":"565","percentOfTotal":1.7357910906298002}},{"age":"18","total":{"people":"1055","percentOfTotal":3.241167434715822},"male":{"people":"545","percentOfTotal":1.6743471582181262},"female":{"people":"510","percentOfTotal":1.566820276497696}},{"age":"19","total":{"people":"1025","percentOfTotal":3.14900153609831},"male":{"people":"495","percentOfTotal":1.5207373271889402},"female":{"people":"530","percentOfTotal":1.6282642089093702}},{"age":"20","total":{"people":"980","percentOfTotal":3.010752688172043},"male":{"people":"520","percentOfTotal":1.597542242703533},"female":{"people":"455","percentOfTotal":1.3978494623655915}},{"age":"21","total":{"people":"890","percentOfTotal":2.7342549923195083},"male":{"people":"485","percentOfTotal":1.4900153609831028},"female":{"people":"410","percentOfTotal":1.2596006144393241}},{"age":"22","total":{"people":"760","percentOfTotal":2.334869431643625},"male":{"people":"400","percentOfTotal":1.228878648233487},"female":{"people":"365","percentOfTotal":1.1213517665130568}},{"age":"23","total":{"people":"760","percentOfTotal":2.334869431643625},"male":{"people":"395","percentOfTotal":1.2135176651305684},"female":{"people":"365","percentOfTotal":1.1213517665130568}},{"age":"24","total":{"people":"800","percentOfTotal":2.457757296466974},"male":{"people":"410","percentOfTotal":1.2596006144393241},"female":{"people":"390","percentOfTotal":1.19815668202765}},{"age":"25","total":{"people":"765","percentOfTotal":2.3502304147465436},"male":{"people":"385","percentOfTotal":1.1827956989247312},"female":{"people":"380","percentOfTotal":1.1674347158218126}},{"age":"26","total":{"people":"745","percentOfTotal":2.2887864823348694},"male":{"people":"380","percentOfTotal":1.1674347158218126},"female":{"people":"365","percentOfTotal":1.1213517665130568}},{"age":"27","total":{"people":"795","percentOfTotal":2.442396313364055},"male":{"people":"400","percentOfTotal":1.228878648233487},"female":{"people":"400","percentOfTotal":1.228878648233487}},{"age":"28","total":{"people":"850","percentOfTotal":2.61136712749616},"male":{"people":"435","percentOfTotal":1.336405529953917},"female":{"people":"415","percentOfTotal":1.2749615975422428}},{"age":"29","total":{"people":"850","percentOfTotal":2.61136712749616},"male":{"people":"385","percentOfTotal":1.1827956989247312},"female":{"people":"465","percentOfTotal":1.4285714285714286}},{"age":"30","total":{"people":"880","percentOfTotal":2.7035330261136714},"male":{"people":"430","percentOfTotal":1.3210445468509986},"female":{"people":"455","percentOfTotal":1.3978494623655915}},{"age":"31","total":{"people":"835","percentOfTotal":2.565284178187404},"male":{"people":"405","percentOfTotal":1.2442396313364055},"female":{"people":"430","percentOfTotal":1.3210445468509986}},{"age":"32","total":{"people":"865","percentOfTotal":2.6574500768049156},"male":{"people":"435","percentOfTotal":1.336405529953917},"female":{"people":"425","percentOfTotal":1.30568356374808}},{"age":"33","total":{"people":"865","percentOfTotal":2.6574500768049156},"male":{"people":"390","percentOfTotal":1.19815668202765},"female":{"people":"470","percentOfTotal":1.4439324116743473}},{"age":"34","total":{"people":"845","percentOfTotal":2.596006144393241},"male":{"people":"440","percentOfTotal":1.3517665130568357},"female":{"people":"410","percentOfTotal":1.2596006144393241}},{"age":"35","total":{"people":"855","percentOfTotal":2.6267281105990783},"male":{"people":"430","percentOfTotal":1.3210445468509986},"female":{"people":"425","percentOfTotal":1.30568356374808}},{"age":"36","total":{"people":"885","percentOfTotal":2.71889400921659},"male":{"people":"450","percentOfTotal":1.3824884792626728},"female":{"people":"435","percentOfTotal":1.336405529953917}},{"age":"37","total":{"people":"905","percentOfTotal":2.7803379416282645},"male":{"people":"450","percentOfTotal":1.3824884792626728},"female":{"people":"455","percentOfTotal":1.3978494623655915}},{"age":"38","total":{"people":"900","percentOfTotal":2.7649769585253456},"male":{"people":"460","percentOfTotal":1.41321044546851},"female":{"people":"440","percentOfTotal":1.3517665130568357}},{"age":"39","total":{"people":"850","percentOfTotal":2.61136712749616},"male":{"people":"425","percentOfTotal":1.30568356374808},"female":{"people":"425","percentOfTotal":1.30568356374808}},{"age":"40","total":{"people":"865","percentOfTotal":2.6574500768049156},"male":{"people":"425","percentOfTotal":1.30568356374808},"female":{"people":"445","percentOfTotal":1.3671274961597542}},{"age":"41","total":{"people":"910","percentOfTotal":2.795698924731183},"male":{"people":"450","percentOfTotal":1.3824884792626728},"female":{"people":"465","percentOfTotal":1.4285714285714286}},{"age":"42","total":{"people":"870","percentOfTotal":2.672811059907834},"male":{"people":"450","percentOfTotal":1.3824884792626728},"female":{"people":"415","percentOfTotal":1.2749615975422428}},{"age":"43","total":{"people":"815","percentOfTotal":2.5038402457757294},"male":{"people":"415","percentOfTotal":1.2749615975422428},"female":{"people":"405","percentOfTotal":1.2442396313364055}},{"age":"44","total":{"people":"780","percentOfTotal":2.3963133640553},"male":{"people":"365","percentOfTotal":1.1213517665130568},"female":{"people":"415","percentOfTotal":1.2749615975422428}},{"age":"45","total":{"people":"885","percentOfTotal":2.71889400921659},"male":{"people":"455","percentOfTotal":1.3978494623655915},"female":{"people":"435","percentOfTotal":1.336405529953917}},{"age":"46","total":{"people":"960","percentOfTotal":2.9493087557603688},"male":{"people":"460","percentOfTotal":1.41321044546851},"female":{"people":"500","percentOfTotal":1.5360983102918586}},{"age":"47","total":{"people":"1000","percentOfTotal":3.0721966205837172},"male":{"people":"535","percentOfTotal":1.6436251920122886},"female":{"people":"465","percentOfTotal":1.4285714285714286}},{"age":"48","total":{"people":"930","percentOfTotal":2.857142857142857},"male":{"people":"460","percentOfTotal":1.41321044546851},"female":{"people":"470","percentOfTotal":1.4439324116743473}},{"age":"49","total":{"people":"950","percentOfTotal":2.9185867895545314},"male":{"people":"475","percentOfTotal":1.4592933947772657},"female":{"people":"475","percentOfTotal":1.4592933947772657}},{"age":"50","total":{"people":"905","percentOfTotal":2.7803379416282645},"male":{"people":"470","percentOfTotal":1.4439324116743473},"female":{"people":"440","percentOfTotal":1.3517665130568357}},{"age":"51","total":{"people":"925","percentOfTotal":2.8417818740399383},"male":{"people":"480","percentOfTotal":1.4746543778801844},"female":{"people":"445","percentOfTotal":1.3671274961597542}},{"age":"52","total":{"people":"845","percentOfTotal":2.596006144393241},"male":{"people":"440","percentOfTotal":1.3517665130568357},"female":{"people":"405","percentOfTotal":1.2442396313364055}},{"age":"53","total":{"people":"830","percentOfTotal":2.5499231950844856},"male":{"people":"435","percentOfTotal":1.336405529953917},"female":{"people":"390","percentOfTotal":1.19815668202765}},{"age":"54","total":{"people":"830","percentOfTotal":2.5499231950844856},"male":{"people":"410","percentOfTotal":1.2596006144393241},"female":{"people":"420","percentOfTotal":1.2903225806451613}},{"age":"55","total":{"people":"755","percentOfTotal":2.3195084485407067},"male":{"people":"400","percentOfTotal":1.228878648233487},"female":{"people":"355","percentOfTotal":1.0906298003072197}},{"age":"56","total":{"people":"770","percentOfTotal":2.3655913978494625},"male":{"people":"390","percentOfTotal":1.19815668202765},"female":{"people":"375","percentOfTotal":1.1520737327188941}},{"age":"57","total":{"people":"720","percentOfTotal":2.2119815668202767},"male":{"people":"355","percentOfTotal":1.0906298003072197},"female":{"people":"365","percentOfTotal":1.1213517665130568}},{"age":"58","total":{"people":"675","percentOfTotal":2.0737327188940093},"male":{"people":"335","percentOfTotal":1.0291858678955454},"female":{"people":"345","percentOfTotal":1.0599078341013823}},{"age":"59","total":{"people":"695","percentOfTotal":2.1351766513056836},"male":{"people":"340","percentOfTotal":1.044546850998464},"female":{"people":"355","percentOfTotal":1.0906298003072197}},{"age":"60","total":{"people":"605","percentOfTotal":1.8586789554531489},"male":{"people":"315","percentOfTotal":0.967741935483871},"female":{"people":"295","percentOfTotal":0.9062980030721967}},{"age":"61","total":{"people":"535","percentOfTotal":1.6436251920122886},"male":{"people":"280","percentOfTotal":0.8602150537634409},"female":{"people":"255","percentOfTotal":0.783410138248848}},{"age":"62","total":{"people":"565","percentOfTotal":1.7357910906298002},"male":{"people":"275","percentOfTotal":0.8448540706605223},"female":{"people":"300","percentOfTotal":0.9216589861751152}},{"age":"63","total":{"people":"575","percentOfTotal":1.7665130568356373},"male":{"people":"280","percentOfTotal":0.8602150537634409},"female":{"people":"290","percentOfTotal":0.8909370199692781}},{"age":"64","total":{"people":"525","percentOfTotal":1.6129032258064515},"male":{"people":"270","percentOfTotal":0.8294930875576038},"female":{"people":"260","percentOfTotal":0.7987711213517665}},{"age":"65","total":{"people":"505","percentOfTotal":1.5514592933947773},"male":{"people":"275","percentOfTotal":0.8448540706605223},"female":{"people":"225","percentOfTotal":0.6912442396313364}},{"age":"66","total":{"people":"490","percentOfTotal":1.5053763440860215},"male":{"people":"260","percentOfTotal":0.7987711213517665},"female":{"people":"230","percentOfTotal":0.706605222734255}},{"age":"67","total":{"people":"410","percentOfTotal":1.2596006144393241},"male":{"people":"205","percentOfTotal":0.6298003072196621},"female":{"people":"205","percentOfTotal":0.6298003072196621}},{"age":"68","total":{"people":"420","percentOfTotal":1.2903225806451613},"male":{"people":"205","percentOfTotal":0.6298003072196621},"female":{"people":"215","percentOfTotal":0.6605222734254993}},{"age":"69","total":{"people":"395","percentOfTotal":1.2135176651305684},"male":{"people":"205","percentOfTotal":0.6298003072196621},"female":{"people":"190","percentOfTotal":0.5837173579109063}},{"age":"70","total":{"people":"355","percentOfTotal":1.0906298003072197},"male":{"people":"185","percentOfTotal":0.5683563748079877},"female":{"people":"170","percentOfTotal":0.522273425499232}},{"age":"71","total":{"people":"320","percentOfTotal":0.9831029185867896},"male":{"people":"155","percentOfTotal":0.4761904761904762},"female":{"people":"165","percentOfTotal":0.5069124423963134}},{"age":"72","total":{"people":"320","percentOfTotal":0.9831029185867896},"male":{"people":"145","percentOfTotal":0.44546850998463905},"female":{"people":"175","percentOfTotal":0.5376344086021506}},{"age":"73","total":{"people":"310","percentOfTotal":0.9523809523809524},"male":{"people":"165","percentOfTotal":0.5069124423963134},"female":{"people":"145","percentOfTotal":0.44546850998463905}},{"age":"74","total":{"people":"270","percentOfTotal":0.8294930875576038},"male":{"people":"130","percentOfTotal":0.39938556067588327},"female":{"people":"140","percentOfTotal":0.43010752688172044}},{"age":"75","total":{"people":"270","percentOfTotal":0.8294930875576038},"male":{"people":"125","percentOfTotal":0.38402457757296465},"female":{"people":"145","percentOfTotal":0.44546850998463905}},{"age":"76","total":{"people":"270","percentOfTotal":0.8294930875576038},"male":{"people":"130","percentOfTotal":0.39938556067588327},"female":{"people":"140","percentOfTotal":0.43010752688172044}},{"age":"77","total":{"people":"220","percentOfTotal":0.6758832565284179},"male":{"people":"85","percentOfTotal":0.261136712749616},"female":{"people":"130","percentOfTotal":0.39938556067588327}},{"age":"78","total":{"people":"230","percentOfTotal":0.706605222734255},"male":{"people":"105","percentOfTotal":0.3225806451612903},"female":{"people":"125","percentOfTotal":0.38402457757296465}},{"age":"79","total":{"people":"215","percentOfTotal":0.6605222734254993},"male":{"people":"110","percentOfTotal":0.3379416282642089},"female":{"people":"105","percentOfTotal":0.3225806451612903}},{"age":"80","total":{"people":"190","percentOfTotal":0.5837173579109063},"male":{"people":"90","percentOfTotal":0.2764976958525346},"female":{"people":"105","percentOfTotal":0.3225806451612903}},{"age":"81","total":{"people":"195","percentOfTotal":0.599078341013825},"male":{"people":"80","percentOfTotal":0.2457757296466974},"female":{"people":"110","percentOfTotal":0.3379416282642089}},{"age":"82","total":{"people":"185","percentOfTotal":0.5683563748079877},"male":{"people":"80","percentOfTotal":0.2457757296466974},"female":{"people":"105","percentOfTotal":0.3225806451612903}},{"age":"83","total":{"people":"180","percentOfTotal":0.5529953917050692},"male":{"people":"75","percentOfTotal":0.2304147465437788},"female":{"people":"110","percentOfTotal":0.3379416282642089}},{"age":"84","total":{"people":"140","percentOfTotal":0.43010752688172044},"male":{"people":"45","percentOfTotal":0.1382488479262673},"female":{"people":"95","percentOfTotal":0.29185867895545314}},{"age":"85","total":{"people":"130","percentOfTotal":0.39938556067588327},"male":{"people":"50","percentOfTotal":0.15360983102918588},"female":{"people":"80","percentOfTotal":0.2457757296466974}},{"age":"86","total":{"people":"125","percentOfTotal":0.38402457757296465},"male":{"people":"50","percentOfTotal":0.15360983102918588},"female":{"people":"75","percentOfTotal":0.2304147465437788}},{"age":"87","total":{"people":"115","percentOfTotal":0.3533026113671275},"male":{"people":"50","percentOfTotal":0.15360983102918588},"female":{"people":"65","percentOfTotal":0.19969278033794163}},{"age":"88","total":{"people":"95","percentOfTotal":0.29185867895545314},"male":{"people":"25","percentOfTotal":0.07680491551459294},"female":{"people":"75","percentOfTotal":0.2304147465437788}},{"age":"89","total":{"people":"95","percentOfTotal":0.29185867895545314},"male":{"people":"40","percentOfTotal":0.1228878648233487},"female":{"people":"55","percentOfTotal":0.16897081413210446}},{"age":"90","total":{"people":"80","percentOfTotal":0.2457757296466974},"male":{"people":"25","percentOfTotal":0.07680491551459294},"female":{"people":"55","percentOfTotal":0.16897081413210446}},{"age":"91","total":{"people":"65","percentOfTotal":0.19969278033794163},"male":{"people":"20","percentOfTotal":0.06144393241167435},"female":{"people":"45","percentOfTotal":0.1382488479262673}},{"age":"92","total":{"people":"50","percentOfTotal":0.15360983102918588},"male":{"people":"15","percentOfTotal":0.04608294930875576},"female":{"people":"30","percentOfTotal":0.09216589861751152}},{"age":"93","total":{"people":"55","percentOfTotal":0.16897081413210446},"male":{"people":"20","percentOfTotal":0.06144393241167435},"female":{"people":"40","percentOfTotal":0.1228878648233487}},{"age":"94","total":{"people":"25","percentOfTotal":0.07680491551459294},"male":{"people":"5","percentOfTotal":0.015360983102918587},"female":{"people":"25","percentOfTotal":0.07680491551459294}},{"age":"95","total":{"people":"10","percentOfTotal":0.030721966205837174},"male":{"people":"0","percentOfTotal":0.0},"female":{"people":"10","percentOfTotal":0.030721966205837174}},{"age":"96","total":{"people":"20","percentOfTotal":0.06144393241167435},"male":{"people":"0","percentOfTotal":0.0},"female":{"people":"15","percentOfTotal":0.04608294930875576}},{"age":"97","total":{"people":"5","percentOfTotal":0.015360983102918587},"male":{"people":"0","percentOfTotal":0.0},"female":{"people":"5","percentOfTotal":0.015360983102918587}},{"age":"98","total":{"people":"10","percentOfTotal":0.030721966205837174},"male":{"people":"0","percentOfTotal":0.0},"female":{"people":"10","percentOfTotal":0.030721966205837174}},{"age":"99","total":{"people":"0","percentOfTotal":0.0},"male":{"people":"5","percentOfTotal":0.015360983102918587},"female":{"people":"5","percentOfTotal":0.015360983102918587}},{"age":"100+","total":{"people":"10","percentOfTotal":0.030721966205837174},"male":{"people":"0","percentOfTotal":0.0},"female":{"people":"5","percentOfTotal":0.015360983102918587}}]